{
  "code": "412133",
  "records": [
    {
      "code": "412133",
      "file": "areacodes/data/1981.txt",
      "level": "county",
      "level_label": "县级",
      "name": "台前县",
      "parent_code": "412100",
      "path": "河南省/安阳地区/台前县",
      "revision": "1981",
      "source": "areacodes"
    },
    {
      "code": "412133",
      "file": "areacodes/data/1982.txt",
      "level": "county",
      "level_label": "县级",
      "name": "台前县",
      "parent_code": "412100",
      "path": "河南省/安阳地区/台前县",
      "revision": "1982",
      "source": "areacodes"
    }
  ]
}