{
  "code": "659006",
  "records": [
    {
      "code": "659006",
      "file": "areacodes/data/2012.txt",
      "level": "county",
      "level_label": "县级",
      "name": "铁门关市",
      "parent_code": "650000",
      "path": "新疆维吾尔自治区/铁门关市",
      "revision": "2012",
      "source": "areacodes"
    },
    {
      "code": "659006",
      "file": "areacodes/data/2013.txt",
      "level": "county",
      "level_label": "县级",
      "name": "铁门关市",
      "parent_code": "650000",
      "path": "新疆维吾尔自治区/铁门关市",
      "revision": "2013",
      "source": "areacodes"
    },
    {
      "code": "659006",
      "file": "areacodes/data/2014.txt",
      "level": "county",
      "level_label": "县级",
      "name": "铁门关市",
      "parent_code": "650000",
      "path": "新疆维吾尔自治区/铁门关市",
      "revision": "2014",
      "source": "areacodes"
    },
    {
      "code": "659006",
      "file": "areacodes/data/2015.txt",
      "level": "county",
      "level_label": "县级",
      "name": "铁门关市",
      "parent_code": "650000",
      "path": "新疆维吾尔自治区/铁门关市",
      "revision": "2015",
      "source": "areacodes"
    },
    {
      "code": "659006",
      "file": "areacodes/data/2016.txt",
      "level": "county",
      "level_label": "县级",
      "name": "铁门关市",
      "parent_code": "650000",
      "path": "新疆维吾尔自治区/铁门关市",
      "revision": "2016",
      "source": "areacodes"
    },
    {
      "code": "659006",
      "file": "areacodes/data/2017.txt",
      "level": "county",
      "level_label": "县级",
      "name": "铁门关市",
      "parent_code": "650000",
      "path": "新疆维吾尔自治区/铁门关市",
      "revision": "2017",
      "source": "areacodes"
    },
    {
      "code": "659006",
      "file": "areacodes/data/2018.txt",
      "level": "county",
      "level_label": "县级",
      "name": "铁门关市",
      "parent_code": "650000",
      "path": "新疆维吾尔自治区/铁门关市",
      "revision": "2018",
      "source": "areacodes"
    },
    {
      "code": "659006",
      "file": "areacodes/data/2019.txt",
      "level": "county",
      "level_label": "县级",
      "name": "铁门关市",
      "parent_code": "650000",
      "path": "新疆维吾尔自治区/铁门关市",
      "revision": "2019",
      "source": "areacodes"
    },
    {
      "code": "659006",
      "file": "areacodes/data/2020.txt",
      "level": "county",
      "level_label": "县级",
      "name": "铁门关市",
      "parent_code": "650000",
      "path": "新疆维吾尔自治区/铁门关市",
      "revision": "2020",
      "source": "areacodes"
    },
    {
      "code": "659006",
      "file": "areacodes/data/2021.txt",
      "level": "county",
      "level_label": "县级",
      "name": "铁门关市",
      "parent_code": "650000",
      "path": "新疆维吾尔自治区/铁门关市",
      "revision": "2021",
      "source": "areacodes"
    },
    {
      "code": "659006",
      "file": "areacodes/data/2022.txt",
      "level": "county",
      "level_label": "县级",
      "name": "铁门关市",
      "parent_code": "650000",
      "path": "新疆维吾尔自治区/铁门关市",
      "revision": "2022",
      "source": "areacodes"
    },
    {
      "code": "659006",
      "file": "areacodes/data/2023.txt",
      "level": "county",
      "level_label": "县级",
      "name": "铁门关市",
      "parent_code": "650000",
      "path": "新疆维吾尔自治区/铁门关市",
      "revision": "2023",
      "source": "areacodes"
    },
    {
      "code": "659006",
      "file": "areacodes/data/2024.txt",
      "level": "county",
      "level_label": "县级",
      "name": "铁门关市",
      "parent_code": "650000",
      "path": "新疆维吾尔自治区/铁门关市",
      "revision": "2024",
      "source": "areacodes"
    },
    {
      "code": "659006",
      "file": "areacodes/data/2025.txt",
      "level": "county",
      "level_label": "县级",
      "name": "铁门关市",
      "parent_code": "650000",
      "path": "新疆维吾尔自治区/铁门关市",
      "revision": "2025",
      "source": "areacodes"
    },
    {
      "code": "659006",
      "file": "gb2260/mca/201112.tsv",
      "level": "county",
      "level_label": "县级",
      "name": "铁门关市",
      "parent_code": "650000",
      "path": "新疆维吾尔自治区/铁门关市",
      "revision": "201112",
      "source": "mca"
    },
    {
      "code": "659006",
      "file": "gb2260/mca/201312.tsv",
      "level": "county",
      "level_label": "县级",
      "name": "铁门关市",
      "parent_code": "650000",
      "path": "新疆维吾尔自治区/铁门关市",
      "revision": "201312",
      "source": "mca"
    },
    {
      "code": "659006",
      "file": "gb2260/mca/201412.tsv",
      "level": "county",
      "level_label": "县级",
      "name": "铁门关市",
      "parent_code": "650000",
      "path": "新疆维吾尔自治区/铁门关市",
      "revision": "201412",
      "source": "mca"
    },
    {
      "code": "659006",
      "file": "gb2260/mca/201501.tsv",
      "level": "county",
      "level_label": "县级",
      "name": "铁门关市",
      "parent_code": "650000",
      "path": "新疆维吾尔自治区/铁门关市",
      "revision": "201501",
      "source": "mca"
    },
    {
      "code": "659006",
      "file": "gb2260/mca/201502.tsv",
      "level": "county",
      "level_label": "县级",
      "name": "铁门关市",
      "parent_code": "650000",
      "path": "新疆维吾尔自治区/铁门关市",
      "revision": "201502",
      "source": "mca"
    },
    {
      "code": "659006",
      "file": "gb2260/mca/201503.tsv",
      "level": "county",
      "level_label": "县级",
      "name": "铁门关市",
      "parent_code": "650000",
      "path": "新疆维吾尔自治区/铁门关市",
      "revision": "201503",
      "source": "mca"
    },
    {
      "code": "659006",
      "file": "gb2260/mca/201504.tsv",
      "level": "county",
      "level_label": "县级",
      "name": "铁门关市",
      "parent_code": "650000",
      "path": "新疆维吾尔自治区/铁门关市",
      "revision": "201504",
      "source": "mca"
    },
    {
      "code": "659006",
      "file": "gb2260/mca/201505.tsv",
      "level": "county",
      "level_label": "县级",
      "name": "铁门关市",
      "parent_code": "650000",
      "path": "新疆维吾尔自治区/铁门关市",
      "revision": "201505",
      "source": "mca"
    },
    {
      "code": "659006",
      "file": "gb2260/mca/201506.tsv",
      "level": "county",
      "level_label": "县级",
      "name": "铁门关市",
      "parent_code": "650000",
      "path": "新疆维吾尔自治区/铁门关市",
      "revision": "201506",
      "source": "mca"
    },
    {
      "code": "659006",
      "file": "gb2260/mca/201507.tsv",
      "level": "county",
      "level_label": "县级",
      "name": "铁门关市",
      "parent_code": "650000",
      "path": "新疆维吾尔自治区/铁门关市",
      "revision": "201507",
      "source": "mca"
    },
    {
      "code": "659006",
      "file": "gb2260/mca/201508.tsv",
      "level": "county",
      "level_label": "县级",
      "name": "铁门关市",
      "parent_code": "650000",
      "path": "新疆维吾尔自治区/铁门关市",
      "revision": "201508",
      "source": "mca"
    },
    {
      "code": "659006",
      "file": "gb2260/mca/201509.tsv",
      "level": "county",
      "level_label": "县级",
      "name": "铁门关市",
      "parent_code": "650000",
      "path": "新疆维吾尔自治区/铁门关市",
      "revision": "201509",
      "source": "mca"
    },
    {
      "code": "659006",
      "file": "gb2260/mca/201510.tsv",
      "level": "county",
      "level_label": "县级",
      "name": "铁门关市",
      "parent_code": "650000",
      "path": "新疆维吾尔自治区/铁门关市",
      "revision": "201510",
      "source": "mca"
    },
    {
      "code": "659006",
      "file": "gb2260/mca/201511.tsv",
      "level": "county",
      "level_label": "县级",
      "name": "铁门关市",
      "parent_code": "650000",
      "path": "新疆维吾尔自治区/铁门关市",
      "revision": "201511",
      "source": "mca"
    },
    {
      "code": "659006",
      "file": "gb2260/mca/201512.tsv",
      "level": "county",
      "level_label": "县级",
      "name": "铁门关市",
      "parent_code": "650000",
      "path": "新疆维吾尔自治区/铁门关市",
      "revision": "201512",
      "source": "mca"
    },
    {
      "code": "659006",
      "file": "gb2260/mca/201601.tsv",
      "level": "county",
      "level_label": "县级",
      "name": "铁门关市",
      "parent_code": "650000",
      "path": "新疆维吾尔自治区/铁门关市",
      "revision": "201601",
      "source": "mca"
    },
    {
      "code": "659006",
      "file": "gb2260/mca/201602.tsv",
      "level": "county",
      "level_label": "县级",
      "name": "铁门关市",
      "parent_code": "650000",
      "path": "新疆维吾尔自治区/铁门关市",
      "revision": "201602",
      "source": "mca"
    },
    {
      "code": "659006",
      "file": "gb2260/mca/201603.tsv",
      "level": "county",
      "level_label": "县级",
      "name": "铁门关市",
      "parent_code": "650000",
      "path": "新疆维吾尔自治区/铁门关市",
      "revision": "201603",
      "source": "mca"
    },
    {
      "code": "659006",
      "file": "gb2260/mca/201604.tsv",
      "level": "county",
      "level_label": "县级",
      "name": "铁门关市",
      "parent_code": "650000",
      "path": "新疆维吾尔自治区/铁门关市",
      "revision": "201604",
      "source": "mca"
    },
    {
      "code": "659006",
      "file": "gb2260/mca/201605.tsv",
      "level": "county",
      "level_label": "县级",
      "name": "铁门关市",
      "parent_code": "650000",
      "path": "新疆维吾尔自治区/铁门关市",
      "revision": "201605",
      "source": "mca"
    },
    {
      "code": "659006",
      "file": "gb2260/mca/201606.tsv",
      "level": "county",
      "level_label": "县级",
      "name": "铁门关市",
      "parent_code": "650000",
      "path": "新疆维吾尔自治区/铁门关市",
      "revision": "201606",
      "source": "mca"
    },
    {
      "code": "659006",
      "file": "gb2260/mca/201607.tsv",
      "level": "county",
      "level_label": "县级",
      "name": "铁门关市",
      "parent_code": "650000",
      "path": "新疆维吾尔自治区/铁门关市",
      "revision": "201607",
      "source": "mca"
    },
    {
      "code": "659006",
      "file": "gb2260/mca/201608.tsv",
      "level": "county",
      "level_label": "县级",
      "name": "铁门关市",
      "parent_code": "650000",
      "path": "新疆维吾尔自治区/铁门关市",
      "revision": "201608",
      "source": "mca"
    },
    {
      "code": "659006",
      "file": "gb2260/mca/201609.tsv",
      "level": "county",
      "level_label": "县级",
      "name": "铁门关市",
      "parent_code": "650000",
      "path": "新疆维吾尔自治区/铁门关市",
      "revision": "201609",
      "source": "mca"
    },
    {
      "code": "659006",
      "file": "gb2260/mca/201610.tsv",
      "level": "county",
      "level_label": "县级",
      "name": "铁门关市",
      "parent_code": "650000",
      "path": "新疆维吾尔自治区/铁门关市",
      "revision": "201610",
      "source": "mca"
    },
    {
      "code": "659006",
      "file": "gb2260/mca/201611.tsv",
      "level": "county",
      "level_label": "县级",
      "name": "铁门关市",
      "parent_code": "650000",
      "path": "新疆维吾尔自治区/铁门关市",
      "revision": "201611",
      "source": "mca"
    },
    {
      "code": "659006",
      "file": "gb2260/mca/201612.tsv",
      "level": "county",
      "level_label": "县级",
      "name": "铁门关市",
      "parent_code": "650000",
      "path": "新疆维吾尔自治区/铁门关市",
      "revision": "201612",
      "source": "mca"
    },
    {
      "code": "659006",
      "file": "gb2260/mca/201701.tsv",
      "level": "county",
      "level_label": "县级",
      "name": "铁门关市",
      "parent_code": "650000",
      "path": "新疆维吾尔自治区/铁门关市",
      "revision": "201701",
      "source": "mca"
    },
    {
      "code": "659006",
      "file": "gb2260/mca/201702.tsv",
      "level": "county",
      "level_label": "县级",
      "name": "铁门关市",
      "parent_code": "650000",
      "path": "新疆维吾尔自治区/铁门关市",
      "revision": "201702",
      "source": "mca"
    },
    {
      "code": "659006",
      "file": "gb2260/mca/201703.tsv",
      "level": "county",
      "level_label": "县级",
      "name": "铁门关市",
      "parent_code": "650000",
      "path": "新疆维吾尔自治区/铁门关市",
      "revision": "201703",
      "source": "mca"
    },
    {
      "code": "659006",
      "file": "gb2260/mca/201704.tsv",
      "level": "county",
      "level_label": "县级",
      "name": "铁门关市",
      "parent_code": "650000",
      "path": "新疆维吾尔自治区/铁门关市",
      "revision": "201704",
      "source": "mca"
    },
    {
      "code": "659006",
      "file": "gb2260/mca/201705.tsv",
      "level": "county",
      "level_label": "县级",
      "name": "铁门关市",
      "parent_code": "650000",
      "path": "新疆维吾尔自治区/铁门关市",
      "revision": "201705",
      "source": "mca"
    },
    {
      "code": "659006",
      "file": "gb2260/mca/201706.tsv",
      "level": "county",
      "level_label": "县级",
      "name": "铁门关市",
      "parent_code": "650000",
      "path": "新疆维吾尔自治区/铁门关市",
      "revision": "201706",
      "source": "mca"
    },
    {
      "code": "659006",
      "file": "gb2260/mca/201707.tsv",
      "level": "county",
      "level_label": "县级",
      "name": "铁门关市",
      "parent_code": "650000",
      "path": "新疆维吾尔自治区/铁门关市",
      "revision": "201707",
      "source": "mca"
    },
    {
      "code": "659006",
      "file": "gb2260/mca/201708.tsv",
      "level": "county",
      "level_label": "县级",
      "name": "铁门关市",
      "parent_code": "650000",
      "path": "新疆维吾尔自治区/铁门关市",
      "revision": "201708",
      "source": "mca"
    },
    {
      "code": "659006",
      "file": "gb2260/mca/201709.tsv",
      "level": "county",
      "level_label": "县级",
      "name": "铁门关市",
      "parent_code": "650000",
      "path": "新疆维吾尔自治区/铁门关市",
      "revision": "201709",
      "source": "mca"
    },
    {
      "code": "659006",
      "file": "gb2260/mca/201710.tsv",
      "level": "county",
      "level_label": "县级",
      "name": "铁门关市",
      "parent_code": "650000",
      "path": "新疆维吾尔自治区/铁门关市",
      "revision": "201710",
      "source": "mca"
    },
    {
      "code": "659006",
      "file": "gb2260/mca/201711.tsv",
      "level": "county",
      "level_label": "县级",
      "name": "铁门关市",
      "parent_code": "650000",
      "path": "新疆维吾尔自治区/铁门关市",
      "revision": "201711",
      "source": "mca"
    },
    {
      "code": "659006",
      "file": "gb2260/mca/201712.tsv",
      "level": "county",
      "level_label": "县级",
      "name": "铁门关市",
      "parent_code": "650000",
      "path": "新疆维吾尔自治区/铁门关市",
      "revision": "201712",
      "source": "mca"
    },
    {
      "code": "659006",
      "file": "gb2260/mca/201801.tsv",
      "level": "county",
      "level_label": "县级",
      "name": "铁门关市",
      "parent_code": "650000",
      "path": "新疆维吾尔自治区/铁门关市",
      "revision": "201801",
      "source": "mca"
    },
    {
      "code": "659006",
      "file": "gb2260/mca/201904.tsv",
      "level": "county",
      "level_label": "县级",
      "name": "铁门关市",
      "parent_code": "650000",
      "path": "新疆维吾尔自治区/铁门关市",
      "revision": "201904",
      "source": "mca"
    },
    {
      "code": "659006",
      "file": "gb2260/stats/201607.tsv",
      "level": "county",
      "level_label": "县级",
      "name": "铁门关市",
      "parent_code": "659000",
      "path": "新疆维吾尔自治区/自治区直辖县级行政区划/铁门关市",
      "revision": "201607",
      "source": "stats"
    },
    {
      "code": "659006",
      "file": "gb2260/stats/201810.tsv",
      "level": "county",
      "level_label": "县级",
      "name": "铁门关市",
      "parent_code": "659000",
      "path": "新疆维吾尔自治区/自治区直辖县级行政区划/铁门关市",
      "revision": "201810",
      "source": "stats"
    }
  ]
}